{
  ".joe02770": [
    "joe",
    "joe027",
    "j0277",
    "j0e27",
    "jo27",
    "02770"
  ],
  ".kyuki": [
    "Kyuki",
    "Kyu",
    "Ky",
    "DarkKyu",
    "DKyu",
    "KyDark",
    "KyukiD",
    "K.D.",
    "Kyuk"
  ],
  ".mcmonkey": [
    "mcmonkey",
    "mcmonk",
    "mcmon",
    "monkey",
    "mcm",
    "mc",
    "monk",
    "mcmk"
  ],
  ".thegreatmarduk": [
    "marduk",
    "greatmarduk",
    "tgmar",
    "mard",
    "tgm",
    "thegm",
    "gmarduk"
  ],
  "Bad Boy Broke The Spreadsheet": [
    "BadBoy",
    "BBB",
    "BrokeSheet",
    "BadBro",
    "BrokeSS",
    "BadB",
    "BroSp",
    "BBS"
  ],
  "Flaebae": [
    "Flae",
    "Bae",
    "Flaeb",
    "FBae",
    "FlaeBae",
    "F"
  ],
  "Flaeon": [
    "Flae",
    "Flaeon",
    "Flay",
    "Fleo",
    "Faon",
    "Fla"
  ],
  "JBax1899": [
    "JBax",
    "JB",
    "Bax",
    "J1899",
    "Bax1899",
    "JBax19"
  ],
  "Jeremy": [
    "Jerm",
    "Jere",
    "Jem",
    "WoodJ",
    "CarpJ",
    "JWoods",
    "JWood",
    "CarpGuru",
    "JBuilder",
    "JCraft"
  ],
  "Jordan": [
    "Jordan",
    "Jord",
    "J",
    "Jo",
    "Jay",
    "Jordy"
  ],
  "Kentucky Fried Kennedy": [
    "KFK",
    "KentFry",
    "KFKennedy",
    "Kfried",
    "KenKen",
    "KF",
    "KentuckyK",
    "KFriedK",
    "KFKen"
  ],
  "King Bignose": [
    "King",
    "Bignose",
    "KB",
    "KBN",
    "KingBN",
    "Bnose",
    "Typhon",
    "Typh"
  ],
  "Law": [
    "Law",
    "LW",
    "Lw",
    "L",
    "Lawy",
    "Lawz"
  ],
  "Lawrence \"Law\"": [
    "Law",
    "Lawrence",
    "L",
    "Lawy",
    "Lawz"
  ],
  "Lrod": [
    "Lrod",
    "Blank",
    "Hater",
    "B-Hate",
    "Rod",
    "L-Ban",
    "NoBlank",
    "H8Blank"
  ],
  "Lrod Yokcos": [
    "Lrod",
    "Yokcos",
    "Tal",
    "Tali",
    "Blank",
    "Hater",
    "LBH",
    "TY",
    "Rod",
    "Yoko"
  ],
  "Lrod Yokcos [blanket hater]": [
    "Lrod",
    "Yokcos",
    "LrodY",
    "Yok",
    "BlanketH",
    "BHater",
    "LRY",
    "Rod",
    "Yoko"
  ],
  "Monk": [
    "Monk",
    "Mnk",
    "Mon",
    "Mk",
    "Monky",
    "Munky"
  ],
  "Ninety": [
    "Ninety",
    "90",
    "Nty",
    "Nin",
    "Silent90",
    "Lurk90",
    "Observer",
    "NinSilent"
  ],
  "Snail": [
    "Snail",
    "Snl",
    "Snl_og",
    "LegoSnail",
    "OgmoSnail",
    "SnailOG",
    "S_ogmo"
  ],
  "Vlad": [
    "Vlad",
    "V",
    "Vl",
    "Vlady",
    "Vladie",
    "Vladster"
  ],
  "_forester": [
    "_forester",
    "forester",
    "forest",
    "fore",
    "fster",
    "frest",
    "fore1",
    "f_"
  ],
  "adriendittrick": [
    "adri",
    "adriend",
    "adit",
    "adriendit",
    "dittrick",
    "adriGamer",
    "PlayPro",
    "GamerAdri",
    "adriendittrick123"
  ],
  "allisonink": [
    "allisonink",
    "allison",
    "ink",
    "ali",
    "allie",
    "aink",
    "allink"
  ],
  "arsanthania": [
    "arsan",
    "anth",
    "ania",
    "ars",
    "arth",
    "aria",
    "airman",
    "epic",
    "air",
    "man",
    "ape",
    "arso",
    "san"
  ],
  "bingdom": [
    "bingdom",
    "bing",
    "bdm",
    "bingo",
    "dom",
    "cyberbing",
    "cyberdom"
  ],
  "bitzero": [
    "bitzero",
    "bit0",
    "bz",
    "bzero",
    "bitz",
    "bzr",
    "b0"
  ],
  "cantavanda": [
    "cantav",
    "vanda",
    "canda",
    "ctv",
    "canta",
    "vandy",
    "cvanda"
  ],
  "circaurus": [
    "circa",
    "raurus",
    "cc",
    "cici",
    "rauri",
    "circy",
    "aury"
  ],
  "danosaur": [
    "dano",
    "saur",
    "danny",
    "hanzoD",
    "danoHan",
    "daz",
    "danoz",
    "hanD",
    "dSaur"
  ],
  "des.c": [
    "des",
    "desc",
    "des_c",
    "dsc",
    "dc"
  ],
  "electrodeoxys": [
    "electro",
    "eoxys",
    "eoxy",
    "electroox",
    "eox",
    "eo",
    "electroair",
    "airman",
    "epicair"
  ],
  "gamesaucer": [
    "gsaucer",
    "dwarfSaucer",
    "shortSaucer",
    "gSaucer",
    "dwarfG",
    "shortG",
    "saucer",
    "gs",
    "dS",
    "sS"
  ],
  "happa.": [
    "happa",
    "hap",
    "sizzle",
    "sizz",
    "cheeks",
    "turt",
    "turtle",
    "dock",
    "ui",
    "soy",
    "bean"
  ],
  "im": [
    "im",
    "IM",
    "GamerX",
    "RetroX",
    "NostX",
    "GX",
    "RG",
    "NP",
    "iG",
    "imX"
  ],
  "ironiccly": [
    "ironic",
    "ironc",
    "ironcly",
    "ironicc",
    "icly",
    "ircly",
    "irncl",
    "irc"
  ],
  "jbax1899": [
    "jbax",
    "jbax18",
    "jbax99",
    "jbx",
    "jax",
    "airman",
    "airm",
    "epic",
    "rocky",
    "rfelle",
    "rfel"
  ],
  "jennasariah": [
    "jen",
    "jenna",
    "jenn",
    "jens",
    "sariah",
    "jariah",
    "jsariah",
    "jjs",
    "jensar",
    "jensariah"
  ],
  "joe": [
    "joe",
    "jo",
    "j",
    "joey",
    "jojo"
  ],
  "joe02770": [
    "Joe",
    "joe0",
    "joe27",
    "joe77",
    "j0277",
    "j0e27",
    "joe027",
    "jo27",
    "joe7"
  ],
  "kepons": [
    "kepons",
    "keps",
    "kpn",
    "kepo",
    "keppy"
  ],
  "klepto_void": [
    "klepto",
    "void",
    "kv",
    "klept",
    "vlad",
    "stew",
    "sb",
    "weeb",
    "kvd",
    "klv",
    "stewb"
  ],
  "lavendernerd": [
    "lavnerd",
    "lav",
    "lnrd",
    "lavvy",
    "yokcos",
    "lavn"
  ],
  "libertea": [
    "libertea",
    "liber",
    "tea",
    "lib",
    "lt",
    "libt"
  ],
  "lukan.spellweaver": [
    "lukan",
    "luka",
    "spell",
    "weaver",
    "lukan.spell",
    "spellweaver",
    "mobius",
    "deer",
    "mobdeer",
    "lsp",
    "lsw"
  ],
  "magnus_m.": [
    "magnus",
    "mag",
    "m_m",
    "mags",
    "m_magnus",
    "mag_m"
  ],
  "mcmonkey": [
    "mc",
    "monk",
    "mcmonk",
    "mcm",
    "monkey",
    "yok",
    "yoky",
    "yokcos",
    "ninety",
    "90",
    "n9"
  ],
  "mercerenies": [
    "merc",
    "mercer",
    "mercy",
    "kenny",
    "typh",
    "typho",
    "kfken",
    "kfck",
    "mercen"
  ],
  "nehemek": [
    "nehemek",
    "nehe",
    "mek",
    "nkm",
    "nek"
  ],
  "ninety_": [
    "ninety",
    "90",
    "nnty",
    "nitey",
    "nty",
    "n9ty"
  ],
  "nocturne_mark": [
    "nocturne",
    "noct",
    "n_mark",
    "n_m",
    "mark",
    "nm",
    "noctm"
  ],
  "pilot": [
    "pilot",
    "plt",
    "turtle",
    "stoner",
    "skibidi",
    "sigma",
    "ninety",
    "90"
  ],
  "plaxus": [
    "plax",
    "plaxu",
    "plaxus",
    "pxus",
    "plx",
    "plxus"
  ],
  "popacristian": [
    "popa",
    "crist",
    "pc",
    "popac",
    "cristian",
    "pcrist",
    "popacri",
    "pcgamer",
    "gifmaster",
    "popadev"
  ],
  "pqp239": [
    "pqp",
    "pq",
    "pqp2",
    "kyu",
    "kyuki",
    "pqp239"
  ],
  "rekko": [
    "rek",
    "rekko",
    "rekki",
    "rekster",
    "rekkoChan",
    "rkk",
    "rekkoC"
  ],
  "rockyfelle": [
    "rocky",
    "rock",
    "rfelle",
    "kinkyrock",
    "vegrock",
    "rockvf",
    "rf"
  ],
  "roxy_robot": [
    "roxy",
    "roxybot",
    "rrobot",
    "rox",
    "rxy",
    "robot",
    "fembot",
    "traprox"
  ],
  "roy5617": [
    "roy",
    "roy5",
    "r5617",
    "luk",
    "lukas",
    "rluk"
  ],
  "roy5654": [
    "roy",
    "roy56",
    "clown",
    "clownroy",
    "rclown",
    "5654"
  ],
  "shawb": [
    "shawb",
    "shaw",
    "jb",
    "jord",
    "manlet",
    "shw"
  ],
  "squarebit": [
    "sqbit",
    "sbit",
    "square",
    "sqb",
    "bit",
    "sq"
  ],
  "squaredbits": [
    "sqbits",
    "squared",
    "sqrd",
    "bits",
    "sqb",
    "sqrdbits",
    "sqbits",
    "sqbts"
  ],
  "squärebean": [
    "squarebean",
    "sqbean",
    "sqb",
    "bean",
    "sbean",
    "sqrebean"
  ],
  "taizen": [
    "taizen",
    "tai",
    "zen",
    "taz",
    "tz"
  ],
  "thelordofmelons95": [
    "melonlord95",
    "melonmath",
    "mlord95",
    "melonking",
    "mathmelon",
    "tlom95",
    "melonboss",
    "lordmelon",
    "melon95",
    "tlom"
  ],
  "tsukayuriko": [
    "tsuka",
    "yuri",
    "yuriko",
    "tsukayuri",
    "tsundere",
    "yuritsuka",
    "tsyuri",
    "tsyuriko"
  ],
  "typhon5919": [
    "Typh",
    "Typh59",
    "Typh19",
    "T5919",
    "TYP",
    "Typho",
    "Typho19",
    "KingBN",
    "Bignose",
    "Shawb",
    "Carrier",
    "Pidge",
    "Law"
  ],
  "tzetsienghwaang": [
    "tzetsieng",
    "tzets",
    "tzhwaang",
    "tzh",
    "tzeng",
    "tzsien",
    "tza",
    "tz"
  ],
  "yokcos": [
    "yok",
    "yoky",
    "cos",
    "rek",
    "Lrod",
    "Yokcos",
    "Ten",
    "Law"
  ]
}